sldc_cytomine/__init__.py
sldc_cytomine/autodetect.py
sldc_cytomine/dump.py
sldc_cytomine/image.py
sldc_cytomine/tile.py
sldc_cytomine/tile_builder.py
sldc_cytomine-2.5.0.dist-info/METADATA
sldc_cytomine-2.5.0.dist-info/WHEEL
sldc_cytomine-2.5.0.dist-info/top_level.txt
sldc_cytomine-2.5.0.dist-info/RECORD
